{
  "resolvedId": "/home/wombocombo/github/wrk/gdg-fsc-website/node_modules/effect/dist/esm/internal/differ/orPatch.js",
  "transforms": [
    {
      "name": "__load__",
      "result": "import * as Chunk from \"../../Chunk.js\";\nimport * as E from \"../../Either.js\";\nimport * as Equal from \"../../Equal.js\";\nimport * as Dual from \"../../Function.js\";\nimport { Structural } from \"../data.js\";\n/** @internal */\nexport const OrPatchTypeId = /*#__PURE__*/Symbol.for(\"effect/DifferOrPatch\");\nfunction variance(a) {\n  return a;\n}\n/** @internal */\nconst PatchProto = {\n  ...Structural.prototype,\n  [OrPatchTypeId]: {\n    _Value: variance,\n    _Key: variance,\n    _Patch: variance\n  }\n};\nconst EmptyProto = /*#__PURE__*/Object.assign(/*#__PURE__*/Object.create(PatchProto), {\n  _tag: \"Empty\"\n});\nconst _empty = /*#__PURE__*/Object.create(EmptyProto);\n/** @internal */\nexport const empty = () => _empty;\nconst AndThenProto = /*#__PURE__*/Object.assign(/*#__PURE__*/Object.create(PatchProto), {\n  _tag: \"AndThen\"\n});\n/** @internal */\nexport const makeAndThen = (first, second) => {\n  const o = Object.create(AndThenProto);\n  o.first = first;\n  o.second = second;\n  return o;\n};\nconst SetLeftProto = /*#__PURE__*/Object.assign(/*#__PURE__*/Object.create(PatchProto), {\n  _tag: \"SetLeft\"\n});\n/** @internal */\nexport const makeSetLeft = value => {\n  const o = Object.create(SetLeftProto);\n  o.value = value;\n  return o;\n};\nconst SetRightProto = /*#__PURE__*/Object.assign(/*#__PURE__*/Object.create(PatchProto), {\n  _tag: \"SetRight\"\n});\n/** @internal */\nexport const makeSetRight = value => {\n  const o = Object.create(SetRightProto);\n  o.value = value;\n  return o;\n};\nconst UpdateLeftProto = /*#__PURE__*/Object.assign(/*#__PURE__*/Object.create(PatchProto), {\n  _tag: \"UpdateLeft\"\n});\n/** @internal */\nexport const makeUpdateLeft = patch => {\n  const o = Object.create(UpdateLeftProto);\n  o.patch = patch;\n  return o;\n};\nconst UpdateRightProto = /*#__PURE__*/Object.assign(/*#__PURE__*/Object.create(PatchProto), {\n  _tag: \"UpdateRight\"\n});\n/** @internal */\nexport const makeUpdateRight = patch => {\n  const o = Object.create(UpdateRightProto);\n  o.patch = patch;\n  return o;\n};\n/** @internal */\nexport const diff = options => {\n  switch (options.oldValue._tag) {\n    case \"Left\":\n      {\n        switch (options.newValue._tag) {\n          case \"Left\":\n            {\n              const valuePatch = options.left.diff(options.oldValue.left, options.newValue.left);\n              if (Equal.equals(valuePatch, options.left.empty)) {\n                return empty();\n              }\n              return makeUpdateLeft(valuePatch);\n            }\n          case \"Right\":\n            {\n              return makeSetRight(options.newValue.right);\n            }\n        }\n      }\n    case \"Right\":\n      {\n        switch (options.newValue._tag) {\n          case \"Left\":\n            {\n              return makeSetLeft(options.newValue.left);\n            }\n          case \"Right\":\n            {\n              const valuePatch = options.right.diff(options.oldValue.right, options.newValue.right);\n              if (Equal.equals(valuePatch, options.right.empty)) {\n                return empty();\n              }\n              return makeUpdateRight(valuePatch);\n            }\n        }\n      }\n  }\n};\n/** @internal */\nexport const combine = /*#__PURE__*/Dual.dual(2, (self, that) => makeAndThen(self, that));\n/** @internal */\nexport const patch = /*#__PURE__*/Dual.dual(2, (self, {\n  left,\n  oldValue,\n  right\n}) => {\n  if (self._tag === \"Empty\") {\n    return oldValue;\n  }\n  let patches = Chunk.of(self);\n  let result = oldValue;\n  while (Chunk.isNonEmpty(patches)) {\n    const head = Chunk.headNonEmpty(patches);\n    const tail = Chunk.tailNonEmpty(patches);\n    switch (head._tag) {\n      case \"Empty\":\n        {\n          patches = tail;\n          break;\n        }\n      case \"AndThen\":\n        {\n          patches = Chunk.prepend(head.first)(Chunk.prepend(head.second)(tail));\n          break;\n        }\n      case \"UpdateLeft\":\n        {\n          if (result._tag === \"Left\") {\n            result = E.left(left.patch(head.patch, result.left));\n          }\n          patches = tail;\n          break;\n        }\n      case \"UpdateRight\":\n        {\n          if (result._tag === \"Right\") {\n            result = E.right(right.patch(head.patch, result.right));\n          }\n          patches = tail;\n          break;\n        }\n      case \"SetLeft\":\n        {\n          result = E.left(head.value);\n          patches = tail;\n          break;\n        }\n      case \"SetRight\":\n        {\n          result = E.right(head.value);\n          patches = tail;\n          break;\n        }\n    }\n  }\n  return result;\n});\n//# sourceMappingURL=orPatch.js.map",
      "start": 1768772628587,
      "end": 1768772628587
    },
    {
      "name": "sentry-vite-component-name-annotate-plugin",
      "start": 1768772628587,
      "end": 1768772628588,
      "order": "pre"
    },
    {
      "name": "comlink",
      "start": 1768772628620,
      "end": 1768772628621,
      "order": "normal"
    },
    {
      "name": "sentry-vite-bundle-size-optimizations-plugin",
      "start": 1768772628650,
      "end": 1768772628651,
      "order": "normal"
    },
    {
      "name": "vite-plugin-csp-guard",
      "start": 1768772628705,
      "end": 1768772628706,
      "order": "post-post"
    }
  ]
}
