{
  "resolvedId": "/home/wombocombo/github/wrk/gdg-fsc-website/node_modules/effect/dist/esm/Pool.js",
  "transforms": [
    {
      "name": "__load__",
      "result": "import * as internal from \"./internal/pool.js\";\n/**\n * @since 2.0.0\n * @category symbols\n */\nexport const PoolTypeId = internal.PoolTypeId;\n/**\n * Returns `true` if the specified value is a `Pool`, `false` otherwise.\n *\n * @since 2.0.0\n * @category refinements\n */\nexport const isPool = internal.isPool;\n/**\n * Makes a new pool of the specified fixed size. The pool is returned in a\n * `Scope`, which governs the lifetime of the pool. When the pool is shutdown\n * because the `Scope` is closed, the individual items allocated by the pool\n * will be released in some unspecified order.\n *\n * By setting the `concurrency` parameter, you can control the level of concurrent\n * access per pool item. By default, the number of permits is set to `1`.\n *\n * `targetUtilization` determines when to create new pool items. It is a value\n * between 0 and 1, where 1 means only create new pool items when all the existing\n * items are fully utilized.\n *\n * A `targetUtilization` of 0.5 will create new pool items when the existing items are\n * 50% utilized.\n *\n * @since 2.0.0\n * @category constructors\n */\nexport const make = internal.make;\n/**\n * Makes a new pool with the specified minimum and maximum sizes and time to\n * live before a pool whose excess items are not being used will be shrunk\n * down to the minimum size. The pool is returned in a `Scope`, which governs\n * the lifetime of the pool. When the pool is shutdown because the `Scope` is\n * used, the individual items allocated by the pool will be released in some\n * unspecified order.\n *\n * By setting the `concurrency` parameter, you can control the level of concurrent\n * access per pool item. By default, the number of permits is set to `1`.\n *\n * `targetUtilization` determines when to create new pool items. It is a value\n * between 0 and 1, where 1 means only create new pool items when all the existing\n * items are fully utilized.\n *\n * A `targetUtilization` of 0.5 will create new pool items when the existing items are\n * 50% utilized.\n *\n * The `timeToLiveStrategy` determines how items are invalidated. If set to\n * \"creation\", then items are invalidated based on their creation time. If set\n * to \"usage\", then items are invalidated based on pool usage.\n *\n * By default, the `timeToLiveStrategy` is set to \"usage\".\n *\n * ```ts skip-type-checking\n * import { createConnection } from \"mysql2\";\n * import { Duration, Effect, Pool } from \"effect\"\n *\n * const acquireDBConnection = Effect.acquireRelease(\n *   Effect.sync(() => createConnection('mysql://...')),\n *   (connection) => Effect.sync(() => connection.end(() => {})),\n * )\n *\n * const connectionPool = Effect.flatMap(\n *  Pool.makeWithTTL({\n *     acquire: acquireDBConnection,\n *     min: 10,\n *     max: 20,\n *     timeToLive: Duration.seconds(60)\n *   }),\n *   (pool) => pool.get\n * )\n * ```\n *\n * @since 2.0.0\n * @category constructors\n */\nexport const makeWithTTL = internal.makeWithTTL;\n/**\n * Retrieves an item from the pool in a scoped effect. Note that if\n * acquisition fails, then the returned effect will fail for that same reason.\n * Retrying a failed acquisition attempt will repeat the acquisition attempt.\n *\n * @since 2.0.0\n * @category getters\n */\nexport const get = internal.get;\n/**\n * Invalidates the specified item. This will cause the pool to eventually\n * reallocate the item, although this reallocation may occur lazily rather\n * than eagerly.\n *\n * @since 2.0.0\n * @category combinators\n */\nexport const invalidate = internal.invalidate;\n//# sourceMappingURL=Pool.js.map",
      "start": 1768772628414,
      "end": 1768772628414
    },
    {
      "name": "sentry-vite-component-name-annotate-plugin",
      "start": 1768772628414,
      "end": 1768772628416,
      "order": "pre"
    },
    {
      "name": "comlink",
      "start": 1768772628418,
      "end": 1768772628421,
      "order": "normal"
    },
    {
      "name": "sentry-vite-bundle-size-optimizations-plugin",
      "start": 1768772628433,
      "end": 1768772628437,
      "order": "normal"
    },
    {
      "name": "vite-plugin-csp-guard",
      "start": 1768772628477,
      "end": 1768772628479,
      "order": "post-post"
    }
  ]
}
