{
  "resolvedId": "/home/wombocombo/github/wrk/gdg-fsc-website/node_modules/@effect/platform/dist/esm/internal/fetchHttpClient.js",
  "transforms": [
    {
      "name": "__load__",
      "result": "import * as Effect from \"effect/Effect\";\nimport * as FiberRef from \"effect/FiberRef\";\nimport * as Stream from \"effect/Stream\";\nimport * as Headers from \"../Headers.js\";\nimport * as Error from \"../HttpClientError.js\";\nimport * as client from \"./httpClient.js\";\nimport * as internalResponse from \"./httpClientResponse.js\";\n/** @internal */\nexport const fetchTagKey = \"@effect/platform/FetchHttpClient/Fetch\";\n/** @internal */\nexport const requestInitTagKey = \"@effect/platform/FetchHttpClient/FetchOptions\";\nconst fetch = /*#__PURE__*/client.make((request, url, signal, fiber) => {\n  const context = fiber.getFiberRef(FiberRef.currentContext);\n  const fetch = context.unsafeMap.get(fetchTagKey) ?? globalThis.fetch;\n  const options = context.unsafeMap.get(requestInitTagKey) ?? {};\n  const headers = options.headers ? Headers.merge(Headers.fromInput(options.headers), request.headers) : request.headers;\n  const send = body => Effect.map(Effect.tryPromise({\n    try: () => fetch(url, {\n      ...options,\n      method: request.method,\n      headers,\n      body,\n      duplex: request.body._tag === \"Stream\" ? \"half\" : undefined,\n      signal\n    }),\n    catch: cause => new Error.RequestError({\n      request,\n      reason: \"Transport\",\n      cause\n    })\n  }), response => internalResponse.fromWeb(request, response));\n  switch (request.body._tag) {\n    case \"Raw\":\n    case \"Uint8Array\":\n      return send(request.body.body);\n    case \"FormData\":\n      return send(request.body.formData);\n    case \"Stream\":\n      return Effect.flatMap(Stream.toReadableStreamEffect(request.body.stream), send);\n  }\n  return send(undefined);\n});\n/** @internal */\nexport const layer = /*#__PURE__*/client.layerMergedContext(/*#__PURE__*/Effect.succeed(fetch));\n//# sourceMappingURL=fetchHttpClient.js.map",
      "start": 1768772628753,
      "end": 1768772628753
    },
    {
      "name": "sentry-vite-component-name-annotate-plugin",
      "start": 1768772628753,
      "end": 1768772628768,
      "order": "pre"
    },
    {
      "name": "comlink",
      "start": 1768772628770,
      "end": 1768772628785,
      "order": "normal"
    },
    {
      "name": "sentry-vite-bundle-size-optimizations-plugin",
      "start": 1768772628789,
      "end": 1768772628803,
      "order": "normal"
    },
    {
      "name": "vite-plugin-csp-guard",
      "start": 1768772628805,
      "end": 1768772628811,
      "order": "post-post"
    }
  ]
}
